pypomes_logging/__init__.py
pypomes_logging/logging_pomes.py
pypomes_logging-0.7.4.dist-info/METADATA
pypomes_logging-0.7.4.dist-info/WHEEL
pypomes_logging-0.7.4.dist-info/licenses/LICENSE
pypomes_logging-0.7.4.dist-info/RECORD
