Metadata-Version: 2.4
Name: pypomes_logging
Version: 0.7.4
Summary: A collection of Python pomes, penyeach (logging module)
Project-URL: Homepage, https://github.com/TheWiseCoder/PyPomes-Logging
Project-URL: Bug Tracker, https://github.com/TheWiseCoder/PyPomes-Logging/issues
Author-email: GT Nunes <wisecoder01@gmail.com>
License-File: LICENSE
Classifier: License :: OSI Approved :: MIT License
Classifier: Operating System :: OS Independent
Classifier: Programming Language :: Python :: 3
Requires-Python: >=3.14
Requires-Dist: flask>=3.1.2
Requires-Dist: pypomes-core>=3.0.6
